hstt/__init__.py
hstt/__main__.py
hstt/main.py
hstt-0.0.5.data/data/LICENSE
hstt-0.0.5.dist-info/LICENSE
hstt-0.0.5.dist-info/METADATA
hstt-0.0.5.dist-info/WHEEL
hstt-0.0.5.dist-info/entry_points.txt
hstt-0.0.5.dist-info/top_level.txt
hstt-0.0.5.dist-info/RECORD
