Metadata-Version: 2.1
Name: hstt
Version: 0.0.5
Summary: HTTP stress testing tool
Home-page: https://github.com/strayge/hstt
Author: strayge
Author-email: strayge@gmail.com
License: UNKNOWN
Platform: UNKNOWN
Classifier: Programming Language :: Python :: 3.7
Classifier: Programming Language :: Python :: 3.8
Classifier: Programming Language :: Python :: 3.9
Classifier: License :: OSI Approved :: MIT License
Requires-Python: >=3.7
License-File: LICENSE
Requires-Dist: aiohttp
Requires-Dist: windows-curses ; sys_platform == "win32"
